database_backup-0.3.5.dist-info/licenses/LICENSE
db_backup/__init__.py
db_backup/__main__.py
db_backup/main.py
db_backup/app/__init__.py
db_backup/app/backup_use_case.py
db_backup/data/__init__.py
db_backup/data/connection_manager.py
db_backup/data/database_gateway.py
db_backup/data/ssh_tunnel.py
db_backup/data/storage_gateway.py
db_backup/domain/__init__.py
db_backup/domain/database.py
db_backup/interface/__init__.py
db_backup/interface/cli.py
database_backup-0.3.5.dist-info/METADATA
database_backup-0.3.5.dist-info/WHEEL
database_backup-0.3.5.dist-info/entry_points.txt
database_backup-0.3.5.dist-info/top_level.txt
database_backup-0.3.5.dist-info/RECORD
