Metadata-Version: 2.4
Name: database-backup
Version: 0.3.5
Summary: A CLI tool for backing up databases to cloud storage.
Author: Kuldip Satpute
License-Expression: MIT
Project-URL: Homepage, https://github.com/magicstack-llp/db-backup
Project-URL: Repository, https://github.com/magicstack-llp/db-backup
Project-URL: Issues, https://github.com/magicstack-llp/db-backup/issues
Keywords: backup,database,mysql,mysqldump,s3,cli,aws
Classifier: Development Status :: 4 - Beta
Classifier: Intended Audience :: Developers
Classifier: Intended Audience :: System Administrators
Classifier: Topic :: Database
Classifier: Topic :: System :: Archiving :: Backup
Classifier: Programming Language :: Python :: 3
Classifier: Programming Language :: Python :: 3 :: Only
Classifier: Programming Language :: Python :: 3.11
Classifier: Programming Language :: Python :: 3.12
Classifier: Programming Language :: Python :: 3.13
Classifier: Environment :: Console
Classifier: Operating System :: OS Independent
Requires-Python: >=3.10
License-File: LICENSE
Requires-Dist: boto3>=1.34.41
Requires-Dist: click>=8.0.0
Requires-Dist: mysql-connector-python>=8.4.0
Requires-Dist: packaging>=25.0
Requires-Dist: paramiko>=3.4.0
Requires-Dist: python-dotenv>=1.0.0
Dynamic: license-file
